setup.py
src/digimat/__init__.py
src/digimat.crypto.egg-info/PKG-INFO
src/digimat.crypto.egg-info/SOURCES.txt
src/digimat.crypto.egg-info/dependency_links.txt
src/digimat.crypto.egg-info/namespace_packages.txt
src/digimat.crypto.egg-info/not-zip-safe
src/digimat.crypto.egg-info/requires.txt
src/digimat.crypto.egg-info/top_level.txt
src/digimat/crypto/__init__.py
src/digimat/crypto/crypto.py