Metadata-Version: 1.1
Name: digimat.crypto
Version: 0.1.3
Summary: Digimat Crypto
Home-page: http://www.digimat.ch
Author: Frederic Hess
Author-email: fhess@splust.ch
License: PSF
Platform: UNKNOWN
Classifier: Development Status :: 4 - Beta
Classifier: Programming Language :: Python :: 3
